kl_bugly/__init__.py
kl_bugly/bugly.py
kl_bugly/bugly_defs.py
kl_bugly/version.py
kl_bugly-0.0.2.dist-info/LICENSE
kl_bugly-0.0.2.dist-info/METADATA
kl_bugly-0.0.2.dist-info/WHEEL
kl_bugly-0.0.2.dist-info/top_level.txt
kl_bugly-0.0.2.dist-info/RECORD
