Metadata-Version: 2.1
Name: kl-bugly
Version: 0.0.2
Summary: bugly sdk tool
Home-page: 
Author: yuxin.zhang
Author-email: whyzi@qq.com
License: MIT
Classifier: License :: OSI Approved :: MIT License
Classifier: Programming Language :: Python
Classifier: Programming Language :: Python :: 3
Classifier: Programming Language :: Python :: 3.6
Classifier: Programming Language :: Python :: Implementation :: CPython
Classifier: Programming Language :: Python :: Implementation :: PyPy
Requires-Python: >=3.6
License-File: LICENSE
Requires-Dist: selenium ==4.7.2
Requires-Dist: requests-html ==0.10.0
Requires-Dist: requests ==2.27.1
Requires-Dist: pydantic ==1.10.2
